library_entity/__init__.py
library_entity/base.py
library_entity/city.py
library_entity/country.py
library_entity/department.py
library_entity/player.py
library_entity/user.py
library_entity-1.0.4.dist-info/METADATA
library_entity-1.0.4.dist-info/WHEEL
library_entity-1.0.4.dist-info/top_level.txt
library_entity-1.0.4.dist-info/RECORD
